aiidalab_chemshell/__init__.py
aiidalab_chemshell/history.py
aiidalab_chemshell/main.py
aiidalab_chemshell/process.py
aiidalab_chemshell/utils.py
aiidalab_chemshell/common/__init__.py
aiidalab_chemshell/common/chemshell.py
aiidalab_chemshell/common/database.py
aiidalab_chemshell/common/file_handling.py
aiidalab_chemshell/common/navigation.py
aiidalab_chemshell/common/node_viewers.py
aiidalab_chemshell/models/__init__.py
aiidalab_chemshell/models/process.py
aiidalab_chemshell/models/resources.py
aiidalab_chemshell/models/results.py
aiidalab_chemshell/models/structure.py
aiidalab_chemshell/models/workflow.py
aiidalab_chemshell/wizards/__init__.py
aiidalab_chemshell/wizards/main_app.py
aiidalab_chemshell/wizards/resources.py
aiidalab_chemshell/wizards/results.py
aiidalab_chemshell/wizards/structure.py
aiidalab_chemshell/wizards/workflows/__init__.py
aiidalab_chemshell/wizards/workflows/geometry_optimisation.py
aiidalab_chemshell/wizards/workflows/main_view.py
aiidalab_chemshell/wizards/workflows/neb.py
aiidalab_chemshell-0.0.1.dist-info/licenses/LICENSE
aiidalab_chemshell-0.0.1.dist-info/METADATA
aiidalab_chemshell-0.0.1.dist-info/WHEEL
aiidalab_chemshell-0.0.1.dist-info/top_level.txt
aiidalab_chemshell-0.0.1.dist-info/RECORD
