Metadata-Version: 2.4
Name: aiidalab-chemshell
Version: 0.0.1
Summary: AiiDAlab application for ChemShell based workflows
Home-page: https://github.com/stfc/aiidalab-chemshell
Author: Dr. Benjamin T. Speake
Author-email: benjamin.speake@stfc.ac.uk
Project-URL: Logo, https://raw.githubusercontent.com/stfc/aiidalab-chemshell/refs/heads/main/images/alc-100.webp
Project-URL: Source, https://github.com/stfc/aiidalab-chemshell
Project-URL: Bug Tracker, https://github.com/stfc/aiidalab-chemshell/issues
Project-URL: Documentation, https://stfc.github.io/aiidalab-chemshell
Classifier: Framework :: AiiDA
Classifier: Operating System :: OS Independent
Classifier: Programming Language :: Python :: 3
Classifier: Development Status :: 4 - Beta
Requires-Python: >=3.9
License-File: LICENSE
Requires-Dist: aiida-core
Requires-Dist: aiidalab-widgets-base
Requires-Dist: aiida-chemshell>=0.1.5
Provides-Extra: dev
Requires-Dist: pytest>=8.0; extra == "dev"
Requires-Dist: pytest-cov>=6.0; extra == "dev"
Requires-Dist: ruff>=0.11.0; extra == "dev"
Requires-Dist: pre-commit; extra == "dev"
Provides-Extra: docs
Requires-Dist: sphinx>=8.0.2; extra == "docs"
Requires-Dist: piccolo-theme>=0.14.0; extra == "docs"
Requires-Dist: sphinx-toolbox; extra == "docs"
Requires-Dist: numpydoc; extra == "docs"
Dynamic: license-file
